Metadata-Version: 2.0
Name: reportlab-x
Version: 3.4.0.2
Summary: The Reportlab Toolkit
Home-page: http://www.reportlab.com/
Author: Andy Robinson, Robin Becker, the ReportLab team and the community
Author-email: reportlab-users@lists2.reportlab.com
License: BSD license (see license.txt for details), Copyright (c) 2000-2015, ReportLab Inc.
Platform: UNKNOWN
Classifier: Development Status :: 5 - Production/Stable
Classifier: Intended Audience :: Developers
Classifier: License :: OSI Approved :: BSD License
Classifier: Topic :: Printing
Classifier: Topic :: Text Processing :: Markup
Classifier: Programming Language :: Python :: 2
Classifier: Programming Language :: Python :: 2.7
Classifier: Programming Language :: Python :: 3
Classifier: Programming Language :: Python :: 3.3
Classifier: Programming Language :: Python :: 3.4
Classifier: Programming Language :: Python :: 3.5
Classifier: Programming Language :: Python :: 3.6
Requires-Dist: pillow (>=2.4.0)
Requires-Dist: pip (>=1.4.1)
Requires-Dist: setuptools (>=2.2)
